{
  "project_info": {
    "project_number": "1081594703993",
    "project_id": "chatappclone-49f9b",
    "storage_bucket": "chatappclone-49f9b.appspot.com"
  },
  "client": [
    {
      "client_info": {
        "mobilesdk_app_id": "1:1081594703993:android:3614c86e10ff5d0a5524a8",
        "android_client_info": {
          "package_name": "com.example.chatappclone"
        }
      },
      "oauth_client": [],
      "api_key": [
        {
          "current_key": "AIzaSyCCYoEMaNM5pgnh1hq8UjXxsQT1iB25Q3o"
        }
      ],
      "services": {
        "appinvite_service": {
          "other_platform_oauth_client": []
        }
      }
    }
  ],
  "configuration_version": "1"
}